numerous/widgets/__init__.py
numerous/widgets/cli.py
numerous/widgets/loadsave.py
numerous/widgets/py.typed
numerous/widgets/timeline.py
numerous/widgets/advanced/__init__.py
numerous/widgets/advanced/weighted_assessment_survey.py
numerous/widgets/base/__init__.py
numerous/widgets/base/accordion.py
numerous/widgets/base/button.py
numerous/widgets/base/card.py
numerous/widgets/base/chartjs.py
numerous/widgets/base/chat.py
numerous/widgets/base/checkbox.py
numerous/widgets/base/config.py
numerous/widgets/base/container.py
numerous/widgets/base/datetime_picker.py
numerous/widgets/base/datetime_range_picker.py
numerous/widgets/base/dom_element_map.py
numerous/widgets/base/drop_down.py
numerous/widgets/base/html_template.py
numerous/widgets/base/map_selector.py
numerous/widgets/base/markdown_display.py
numerous/widgets/base/markdown_drawer.py
numerous/widgets/base/modal_dialog.py
numerous/widgets/base/number.py
numerous/widgets/base/plotly.py
numerous/widgets/base/progress_bar.py
numerous/widgets/base/radio_buttons.py
numerous/widgets/base/slider.py
numerous/widgets/base/string.py
numerous/widgets/base/table.py
numerous/widgets/base/tabs.py
numerous/widgets/base/task.py
numerous/widgets/base/timer.py
numerous/widgets/base/toast.py
numerous/widgets/base/toggle_button.py
numerous/widgets/base/tree.py
numerous/widgets/base/url_params.py
numerous/widgets/files/__init__.py
numerous/widgets/files/load_save_from_local.py
numerous/widgets/numerous/__init__.py
numerous/widgets/numerous/project.py
numerous/widgets/numerous/projects.py
numerous/widgets/numerous/stress_test_projects.py
numerous/widgets/state/__init__.py
numerous/widgets/state/model.py
numerous/widgets/static/AccordionWidget.mjs
numerous/widgets/static/ButtonWidget.mjs
numerous/widgets/static/ChartWidget.mjs
numerous/widgets/static/ChatWidget.mjs
numerous/widgets/static/CheckBoxWidget.mjs
numerous/widgets/static/DOMElementMapWidget.mjs
numerous/widgets/static/DateTimePickerWidget.mjs
numerous_widgets-0.2.18.dist-info/licenses/LICENSE.md
numerous_widgets-0.2.18.dist-info/METADATA
numerous_widgets-0.2.18.dist-info/WHEEL
numerous_widgets-0.2.18.dist-info/entry_points.txt
numerous_widgets-0.2.18.dist-info/top_level.txt
numerous_widgets-0.2.18.dist-info/RECORD
