Metadata-Version: 2.4
Name: numerous-widgets
Version: 0.2.18
Summary: Widgets and patterns for building apps using frameworks like Panel, Marimo, and Jupyter based on the AnyWidget library.
Author-email: "Lasse Thomsen, Numerous ApS" <lasse.thomsen@numerous.com>
Project-URL: Homepage, https://github.com/pypa/sampleproject
Project-URL: Issues, https://github.com/pypa/sampleproject/issues
Classifier: Programming Language :: Python :: 3
Classifier: Development Status :: 2 - Pre-Alpha
Classifier: Intended Audience :: Developers
Requires-Python: >=3.11
License-File: LICENSE.md
Requires-Dist: anywidget
Requires-Dist: pydantic
Requires-Dist: jinja2
Requires-Dist: h5py
Provides-Extra: dev
Requires-Dist: pre-commit; extra == "dev"
Requires-Dist: black; extra == "dev"
Requires-Dist: mypy; extra == "dev"
Requires-Dist: anywidget[dev]; extra == "dev"
Requires-Dist: python-dotenv; extra == "dev"
Requires-Dist: numerous; extra == "dev"
Requires-Dist: pytest; extra == "dev"
Requires-Dist: ruff==0.6.4; extra == "dev"
Requires-Dist: mypy==1.11.2; extra == "dev"
Requires-Dist: coverage==7.6.1; extra == "dev"
Requires-Dist: twine==5.1.1; extra == "dev"
Requires-Dist: mkdocs==1.6.0; extra == "dev"
Requires-Dist: mkdocstrings==0.26.2; extra == "dev"
Requires-Dist: mkdocstrings-python==1.12.2; extra == "dev"
Requires-Dist: mkdocs_snippet_plugin==1.0.2; extra == "dev"
Requires-Dist: mkdocs-material==9.5.46; extra == "dev"
Requires-Dist: mkdocs-gen-files==0.5.0; extra == "dev"
Requires-Dist: mkdocs-section-index==0.3.9; extra == "dev"
Requires-Dist: mkdocs-literate-nav==0.6.1; extra == "dev"
Requires-Dist: marimo; extra == "dev"
Requires-Dist: panel; extra == "dev"
Dynamic: license-file
